geopatra/__init__.py
geopatra/folium/__init__.py
geopatra/folium/choropleth.py
geopatra/folium/circle.py
geopatra/folium/geojson.py
geopatra/folium/heatmap.py
geopatra/folium/markercluster.py
geopatra/folium/utils.py
geopatra/kepler/__init__.py
geopatra/kepler/config/colors.json
geopatra/kepler/config/geojson.config
geopatra/kepler/geojson.py
geopatra/kepler/utils.py
geopatra/map.py
geopatra-0.3.0.dist-info/LICENSE
geopatra-0.3.0.dist-info/WHEEL
geopatra-0.3.0.dist-info/METADATA
geopatra-0.3.0.dist-info/RECORD
