Metadata-Version: 2.1
Name: geopatra
Version: 0.3.0
Summary: Interactive Maps with Geopandas
Home-page: https://github.com/Sangarshanan/geopatra
Keywords: geopandas,geospatial,interactive maps
Author: sangarshanan
Author-email: sangarshanan1998@gmail.com
Requires-Python: >=3.9,<4.0
Classifier: Programming Language :: Python :: 3
Classifier: Programming Language :: Python :: 3.10
Classifier: Programming Language :: Python :: 3.9
Requires-Dist: folium (>=0.11.0,<0.12.0)
Requires-Dist: geopandas (>=0.8.1,<0.9.0)
Requires-Dist: importlib-metadata (>=1.0,<2.0); python_version >= "3.9"
Requires-Dist: keplergl (>=0.1.2,<0.2.0)
Project-URL: Documentation, https://geopatra.readthedocs.io/
Project-URL: Repository, https://github.com/Sangarshanan/geopatra
